wiphy/__init__.py
wiphy/util/inds/M=2_K=1_Q=2_minh=2_ineq=0.txt
wiphy/util/inds/M=4_K=1_Q=4_minh=2_ineq=0.txt
wiphy/util/inds/M=4_K=2_Q=4_minh=2_ineq=0.txt
wiphy/util/inds/M=4_K=3_Q=4_minh=2_ineq=0.txt
wiphy-0.9.3.dist-info/LICENSE
wiphy-0.9.3.dist-info/METADATA
wiphy-0.9.3.dist-info/WHEEL
wiphy-0.9.3.dist-info/top_level.txt
wiphy-0.9.3.dist-info/RECORD
