Metadata-Version: 2.1
Name: wiphy
Version: 0.9.3
Summary: The fundamental Python package for wireless signal processing at the physical layer
Home-page: https://github.com/ishikawalab/wiphy/
Author: Ishikawa Laboratory
Author-email: contact@ishikawa.cc
License: MIT
Download-URL: https://pypi.org/project/wiphy/
Platform: UNKNOWN
Classifier: License :: OSI Approved :: MIT License
Classifier: Programming Language :: Python :: 3.7
Requires-Dist: numpy
Requires-Dist: pandas
Requires-Dist: scipy
Requires-Dist: sympy
Requires-Dist: numba
Requires-Dist: tqdm
